<?xml version="1.0" encoding="UTF-8" standalone="no"?>
<!--
 Copyright (c) 2023 SAP SE or an SAP affiliate company. All rights reserved.
--><!--
 All hybris buildcallbacks.xml macrodefinitions:

 Build/Documentation

	 before/after ant macro "clean"
		 <macrodef name="b2ctelcomocks_before_clean"/>
		 <macrodef name="b2ctelcomocks_after_clean"/>

	 before/after ant macro "build"
		 <macrodef name="b2ctelcomocks_before_build"/>
		 <macrodef name="b2ctelcomocks_after_build"/>

	 before/after ant macro "compile_core" - the core module of the extension
		 <macrodef name="b2ctelcomocks_before_compile_core">
		 <macrodef name="b2ctelcomocks_after_compile_core">

	 before/after ant macro "compile_web" - the web module of the extension
		 <macrodef name="b2ctelcomocks_before_compile_web" />
		 <macrodef name="b2ctelcomocks_after_compile_web" />

 Preparing extension

	 will be called in the beginning of the ant call and only once (also when using multiple
	 ant targets e.g. ant build yunittest)
		 <macrodef name="b2ctelcomocks_only_once_prepare"/>

 Creating ear module/production

	 before/after ant macro "ear"
		 <macrodef name="b2ctelcomocks_before_ear"/>
		 <macrodef name="b2ctelcomocks_after_ear"/>

	 before/after ant macro "production" - for hybris server only
		 <macrodef name="b2ctelcomocks_before_production" />
		 <macrodef name="b2ctelcomocks_after_production" />

 JUnit Test

	 before/after ant macro "yunitinit"
		 <macrodef name="b2ctelcomocks_before_yunitinit" />
		 <macrodef name="b2ctelcomocks_after_yunitinit" />

	 before/after ant macro "yunit"
		 <macrodef name="b2ctelcomocks_before_yunit" />
		 <macrodef name="b2ctelcomocks_after_yunit" />

 Distribution package

 	 before/after ant macro "dist" - internal target; only for use when platform is available in source code
		 <macrodef name="b2ctelcomocks_after_dist"/>
		 <macrodef name="b2ctelcomocks_before_dist"/>

	 before/after ant macro "dist_copy" - internal target; only for use when platform is available in source code
		 <macrodef name="b2ctelcomocks_before_dist_copy"/>
		 <macrodef name="b2ctelcomocks_after_dist_copy"/>

--><project name="b2ctelcomocks_buildcallbacks">

    <!--OVERRIDING the default macro definition-->
    <macrodef name="extension_build_number">
        <attribute name="extname" />
        <attribute name="destdir" />

        <sequential>
            <!-- Just leave the file as it is declared into the custom extension-->
        </sequential>
    </macrodef>

    <!--
        Called whenever 'ant ear' is used. this callback can be used to modify the content of the ear file

         ${ear.path}: 			path to ear
     -->
    <macrodef name="b2ctelcomocks_before_ear">
        <sequential>

            <!-- you can do anything before the EAR file is being packed -->

        </sequential>
    </macrodef>

</project>
